{
  "source": "willinstructions-new.affinitydns.uk",
  "page_id": 2321,
  "category": "brands-batch2",
  "exported_at": "2026-05-28T23:58:43Z",
  "elementor_data": {
    "json": [
      {
        "id": "931c0be",
        "elType": "container",
        "settings": {
          "container_type": "flex",
          "content_width": "full",
          "flex_direction": "column",
          "padding": {
            "unit": "px",
            "top": "60",
            "right": "40",
            "bottom": "60",
            "left": "40"
          },
          "background_background": "classic",
          "background_color": "#171717",
          "gap": {
            "unit": "px",
            "size": "40"
          },
          "flex_align_items": "center"
        },
        "elements": [
          {
            "id": "260d737",
            "elType": "widget",
            "settings": {
              "html": "<p style='color:#EDEDED;font-size:36px;font-weight:600;font-family:'Inter',sans-serif,serif;text-transform:none;letter-spacing:-1.2px;text-align:center;line-height:1.6;'>WHAT WE DO</p>"
            },
            "elements": [],
            "widgetType": "html"
          },
          {
            "id": "b914bbe",
            "elType": "container",
            "settings": {
              "container_type": "flex",
              "content_width": "full",
              "flex_direction": "row",
              "gap": {
                "unit": "px",
                "size": "16"
              },
              "flex_wrap": "wrap"
            },
            "elements": [
              {
                "id": "2bd68ca",
                "elType": "container",
                "settings": {
                  "container_type": "flex",
                  "content_width": "boxed",
                  "flex_direction": "column",
                  "width": {
                    "unit": "%",
                    "size": 25
                  },
                  "padding": {
                    "unit": "px",
                    "top": "24",
                    "right": "20",
                    "bottom": "24",
                    "left": "20"
                  },
                  "background_background": "classic",
                  "background_color": "#0F0F0F",
                  "gap": {
                    "unit": "px",
                    "size": "12"
                  },
                  "border_border": "solid",
                  "border_width": {
                    "unit": "px",
                    "top": "1",
                    "right": "1",
                    "bottom": "1",
                    "left": "1"
                  },
                  "border_color": "#2A2A2A",
                  "border_radius": {
                    "unit": "px",
                    "top": "8",
                    "right": "8",
                    "bottom": "8",
                    "left": "8"
                  },
                  "flex_align_items": "center"
                },
                "elements": [
                  {
                    "id": "4525d79",
                    "elType": "widget",
                    "settings": {
                      "html": "<p style='color:#3ECF8E;font-size:32px;font-weight:600;font-family:'Inter',sans-serif,serif;text-transform:none;letter-spacing:0px;text-align:left;line-height:1.6;'>01</p>"
                    },
                    "elements": [],
                    "widgetType": "html"
                  },
                  {
                    "id": "71db8d8",
                    "elType": "widget",
                    "settings": {
                      "html": "<p style='color:#EDEDED;font-size:16px;font-weight:700;font-family:'Inter',sans-serif,serif;text-transform:none;letter-spacing:0px;text-align:left;line-height:1.6;'>Strategy</p>"
                    },
                    "elements": [],
                    "widgetType": "html"
                  },
                  {
                    "id": "c2bbc3e",
                    "elType": "widget",
                    "settings": {
                      "html": "<p style='color:#8F8F8F;font-size:14px;font-weight:400;font-family:'Inter',sans-serif,serif;text-transform:none;letter-spacing:0px;text-align:left;line-height:1.6;'>Research-driven insights that guide every decision.</p>"
                    },
                    "elements": [],
                    "widgetType": "html"
                  }
                ],
                "isInner": true
              },
              {
                "id": "bb956ff",
                "elType": "container",
                "settings": {
                  "container_type": "flex",
                  "content_width": "boxed",
                  "flex_direction": "column",
                  "width": {
                    "unit": "%",
                    "size": 25
                  },
                  "padding": {
                    "unit": "px",
                    "top": "24",
                    "right": "20",
                    "bottom": "24",
                    "left": "20"
                  },
                  "background_background": "classic",
                  "background_color": "#0F0F0F",
                  "gap": {
                    "unit": "px",
                    "size": "12"
                  },
                  "border_border": "solid",
                  "border_width": {
                    "unit": "px",
                    "top": "1",
                    "right": "1",
                    "bottom": "1",
                    "left": "1"
                  },
                  "border_color": "#2A2A2A",
                  "border_radius": {
                    "unit": "px",
                    "top": "8",
                    "right": "8",
                    "bottom": "8",
                    "left": "8"
                  },
                  "flex_align_items": "center"
                },
                "elements": [
                  {
                    "id": "5e1f632",
                    "elType": "widget",
                    "settings": {
                      "html": "<p style='color:#3ECF8E;font-size:32px;font-weight:600;font-family:'Inter',sans-serif,serif;text-transform:none;letter-spacing:0px;text-align:left;line-height:1.6;'>02</p>"
                    },
                    "elements": [],
                    "widgetType": "html"
                  },
                  {
                    "id": "354d7fa",
                    "elType": "widget",
                    "settings": {
                      "html": "<p style='color:#EDEDED;font-size:16px;font-weight:700;font-family:'Inter',sans-serif,serif;text-transform:none;letter-spacing:0px;text-align:left;line-height:1.6;'>Design</p>"
                    },
                    "elements": [],
                    "widgetType": "html"
                  },
                  {
                    "id": "89950da",
                    "elType": "widget",
                    "settings": {
                      "html": "<p style='color:#8F8F8F;font-size:14px;font-weight:400;font-family:'Inter',sans-serif,serif;text-transform:none;letter-spacing:0px;text-align:left;line-height:1.6;'>Beautiful interfaces crafted with attention to detail.</p>"
                    },
                    "elements": [],
                    "widgetType": "html"
                  }
                ],
                "isInner": true
              },
              {
                "id": "b78a5b7",
                "elType": "container",
                "settings": {
                  "container_type": "flex",
                  "content_width": "boxed",
                  "flex_direction": "column",
                  "width": {
                    "unit": "%",
                    "size": 25
                  },
                  "padding": {
                    "unit": "px",
                    "top": "24",
                    "right": "20",
                    "bottom": "24",
                    "left": "20"
                  },
                  "background_background": "classic",
                  "background_color": "#0F0F0F",
                  "gap": {
                    "unit": "px",
                    "size": "12"
                  },
                  "border_border": "solid",
                  "border_width": {
                    "unit": "px",
                    "top": "1",
                    "right": "1",
                    "bottom": "1",
                    "left": "1"
                  },
                  "border_color": "#2A2A2A",
                  "border_radius": {
                    "unit": "px",
                    "top": "8",
                    "right": "8",
                    "bottom": "8",
                    "left": "8"
                  },
                  "flex_align_items": "center"
                },
                "elements": [
                  {
                    "id": "0b666b4",
                    "elType": "widget",
                    "settings": {
                      "html": "<p style='color:#3ECF8E;font-size:32px;font-weight:600;font-family:'Inter',sans-serif,serif;text-transform:none;letter-spacing:0px;text-align:left;line-height:1.6;'>03</p>"
                    },
                    "elements": [],
                    "widgetType": "html"
                  },
                  {
                    "id": "3ea66d5",
                    "elType": "widget",
                    "settings": {
                      "html": "<p style='color:#EDEDED;font-size:16px;font-weight:700;font-family:'Inter',sans-serif,serif;text-transform:none;letter-spacing:0px;text-align:left;line-height:1.6;'>Build</p>"
                    },
                    "elements": [],
                    "widgetType": "html"
                  },
                  {
                    "id": "c26c111",
                    "elType": "widget",
                    "settings": {
                      "html": "<p style='color:#8F8F8F;font-size:14px;font-weight:400;font-family:'Inter',sans-serif,serif;text-transform:none;letter-spacing:0px;text-align:left;line-height:1.6;'>Robust solutions built on proven technology.</p>"
                    },
                    "elements": [],
                    "widgetType": "html"
                  }
                ],
                "isInner": true
              },
              {
                "id": "b0234da",
                "elType": "container",
                "settings": {
                  "container_type": "flex",
                  "content_width": "boxed",
                  "flex_direction": "column",
                  "width": {
                    "unit": "%",
                    "size": 25
                  },
                  "padding": {
                    "unit": "px",
                    "top": "24",
                    "right": "20",
                    "bottom": "24",
                    "left": "20"
                  },
                  "background_background": "classic",
                  "background_color": "#0F0F0F",
                  "gap": {
                    "unit": "px",
                    "size": "12"
                  },
                  "border_border": "solid",
                  "border_width": {
                    "unit": "px",
                    "top": "1",
                    "right": "1",
                    "bottom": "1",
                    "left": "1"
                  },
                  "border_color": "#2A2A2A",
                  "border_radius": {
                    "unit": "px",
                    "top": "8",
                    "right": "8",
                    "bottom": "8",
                    "left": "8"
                  },
                  "flex_align_items": "center"
                },
                "elements": [
                  {
                    "id": "eab71fc",
                    "elType": "widget",
                    "settings": {
                      "html": "<p style='color:#3ECF8E;font-size:32px;font-weight:600;font-family:'Inter',sans-serif,serif;text-transform:none;letter-spacing:0px;text-align:left;line-height:1.6;'>04</p>"
                    },
                    "elements": [],
                    "widgetType": "html"
                  },
                  {
                    "id": "a869812",
                    "elType": "widget",
                    "settings": {
                      "html": "<p style='color:#EDEDED;font-size:16px;font-weight:700;font-family:'Inter',sans-serif,serif;text-transform:none;letter-spacing:0px;text-align:left;line-height:1.6;'>Support</p>"
                    },
                    "elements": [],
                    "widgetType": "html"
                  },
                  {
                    "id": "fba24e9",
                    "elType": "widget",
                    "settings": {
                      "html": "<p style='color:#8F8F8F;font-size:14px;font-weight:400;font-family:'Inter',sans-serif,serif;text-transform:none;letter-spacing:0px;text-align:left;line-height:1.6;'>Ongoing partnership for lasting success.</p>"
                    },
                    "elements": [],
                    "widgetType": "html"
                  }
                ],
                "isInner": true
              }
            ],
            "isInner": true
          }
        ],
        "isInner": false
      }
    ]
  }
}